filexl/__init__.py
filexl/cli.py
filexl-1.0.2.dist-info/licenses/LICENSE
filexl-1.0.2.dist-info/METADATA
filexl-1.0.2.dist-info/WHEEL
filexl-1.0.2.dist-info/entry_points.txt
filexl-1.0.2.dist-info/top_level.txt
filexl-1.0.2.dist-info/RECORD
