Metadata-Version: 2.4
Name: filexl
Version: 1.0.2
Summary: CLI tool to list files and export to Excel
Home-page: https://github.com/kiarash-gh/filexl
Author: Kiarash Gharahgozloo
Author-email: kiarash.gh@gmail.com
Classifier: Programming Language :: Python :: 3
Classifier: License :: OSI Approved :: MIT License
Classifier: Operating System :: OS Independent
Requires-Python: >=3.7
License-File: LICENSE
Requires-Dist: pandas
Requires-Dist: openpyxl
Dynamic: author
Dynamic: author-email
Dynamic: classifier
Dynamic: description
Dynamic: description-content-type
Dynamic: home-page
Dynamic: license-file
Dynamic: requires-dist
Dynamic: requires-python
Dynamic: summary
